prepCV/__init__.py
prepCV/auto_preprocessing.py
prepCV/utils.py
prepcv-2.1.0.dist-info/LICENSE
prepcv-2.1.0.dist-info/WHEEL
prepcv-2.1.0.dist-info/METADATA
prepcv-2.1.0.dist-info/RECORD
