Metadata-Version: 2.1
Name: prepCV
Version: 2.1.0
Summary: Define preprocessing pipelines using nested callable functions and parameter grids for them.
Author-email: Kalmy8 <kalmykovalexey01@gmail.com>
Requires-Python: >=3.9
Classifier: Programming Language :: Python :: 3
Classifier: License :: OSI Approved :: MIT License
Requires-Dist: numpy>=2.0.2
Requires-Dist: matplotlib>=3.9.2
Requires-Dist: opencv-python
Requires-Dist: dill
Project-URL: homepage, https://github.com/Kalmy8/auto_preprocessing
